ctp/__init__.py
ctp/conf.py
ctp/ctp.py
ctp/experiment.py
ctp/manager.py
ctp/run.py
ctp/utils.py
ctp/ctp_grpc/__init__.py
ctp/ctp_grpc/ctp_pb2.py
ctp/ctp_grpc/ctp_pb2_grpc.py
cthenp-0.2.0.dist-info/METADATA
cthenp-0.2.0.dist-info/WHEEL
cthenp-0.2.0.dist-info/licenses/LICENSE
cthenp-0.2.0.dist-info/RECORD
