Metadata-Version: 2.1
Name: cthenp
Version: 0.2.0
Summary: A package that collects data then process
Project-URL: Homepage, https://github.com/lrq619/CTP
Project-URL: Bug Tracker, https://github.com/lrq619/CTP/issues
Author-email: LaiRuiqi <lrq619@outlook.com>
License-File: LICENSE
Classifier: License :: OSI Approved :: Apache Software License
Classifier: Operating System :: OS Independent
Classifier: Programming Language :: Python :: 3
Requires-Python: >=3.8
Requires-Dist: google-api-python-client>=2.0.0
Requires-Dist: grpcio>=1.15.0
